overreacher/__init__.py
overreacher/__main__.py
overreacher/arguments.py
overreacher/attacks.py
overreacher/config.py
overreacher/execute.py
overreacher/overreacher.py
overreacher/utilities.py
overreacher/version.py
overreacher/visuals.py
overreacher/data/attacks.json
overreacher/data/config.ini
overreacher-1.0.2.dist-info/licenses/LICENSE
overreacher-1.0.2.dist-info/METADATA
overreacher-1.0.2.dist-info/WHEEL
overreacher-1.0.2.dist-info/entry_points.txt
overreacher-1.0.2.dist-info/top_level.txt
overreacher-1.0.2.dist-info/RECORD
