Metadata-Version: 2.4
Name: OverReacher
Version: 1.0.2
Summary: A scanner for CORS misconfiguration vulnerabilities
Author-email: Zipnx <zipnx@protonmail.com>
Maintainer-email: Zipnx <zipnx@protonmail.com>
Project-URL: Homepage, https://github.com/Zipnx/OverReacher
Project-URL: Repository, https://github.com/Zipnx/OverReacher
Project-URL: Changelog, https://github.com/Zipnx/OverReacher/blob/master/CHANGELOG.md
Keywords: cors,security,pentest,bugbounty,tool,automation
Classifier: Programming Language :: Python
Classifier: Topic :: Security
Classifier: Programming Language :: Python :: 3 :: Only
Requires-Python: >=3.8
License-File: LICENSE
Requires-Dist: requests
Requires-Dist: rich
Requires-Dist: urllib3
Provides-Extra: dev
Requires-Dist: twine; extra == "dev"
Requires-Dist: setuptools; extra == "dev"
Requires-Dist: build; extra == "dev"
Dynamic: license-file
